injector/__init__.py
injector/injector.py
document_variable_injector-0.1.2.dist-info/LICENSE.md
document_variable_injector-0.1.2.dist-info/WHEEL
document_variable_injector-0.1.2.dist-info/METADATA
document_variable_injector-0.1.2.dist-info/RECORD
