Metadata-Version: 2.1
Name: document-variable-injector
Version: 0.1.2
Summary: Provides method for dynamically injecting variables into a document and/or HTML like object
Home-page: https://github.com/alexpdr/document-variable-injector
License: GPL-3.0-or-later
Author: Alex Pedersen
Author-email: me@alexpdr.dev
Maintainer: Alex Pedersen
Maintainer-email: me@alexpdr.dev
Requires-Python: >=3.8,<4.0
Classifier: License :: OSI Approved :: GNU General Public License v3 or later (GPLv3+)
Classifier: Programming Language :: Python :: 3
Classifier: Programming Language :: Python :: 3.8
Project-URL: Repository, https://github.com/alexpdr/document-variable-injector
